sideload_python_3_bin_6776537eacd3cb34a8c2f2ef/__init__.py
sideload_python_3_bin_6776537eacd3cb34a8c2f2ef/python-3.12.8-amd64.exe
sideload_python_3_bin_6776537eacd3cb34a8c2f2ef-1.0.0.dist-info/METADATA
sideload_python_3_bin_6776537eacd3cb34a8c2f2ef-1.0.0.dist-info/WHEEL
sideload_python_3_bin_6776537eacd3cb34a8c2f2ef-1.0.0.dist-info/top_level.txt
sideload_python_3_bin_6776537eacd3cb34a8c2f2ef-1.0.0.dist-info/RECORD
