Metadata-Version: 2.1
Name: sideload_python_3_bin_6776537eacd3cb34a8c2f2ef
Version: 1.0.0
Summary: Sideloaded package
Author: Null Void
Requires-Python: >=3.8
